[
    {
      "children": [
        {
            "componentType": "style",
            "content": "Ensure that your code adheres to the following principles:\n\n1. **Best Practices:**  \n   - Optimize for performance, maintainability, readability, and modularity.\n\n2. **Functional Modularity:**  \n   - Design well-defined, reusable functions to handle discrete tasks.  \n   - Each function must have a single, clear purpose to avoid unnecessary fragmentation.\n\n3. **File Modularity:**  \n   - Organize your codebase across multiple files to reduce complexity and enforce a black-box design.  \n   - Intentionally isolate core modules or specific functionalities into separate files when appropriate that are imported into the main executable.\n\n4. **Comments and Documentation:**  \n   - Begin each file with a comment block that explains its purpose and role within the project.  \n   - Document every function with a comment block that describes its functionality, including inputs and outputs.  \n   - Use inline comments to clarify the purpose and implementation of non-obvious code segments.  \n   - For any external function calls (functions not defined within the current file), include a comment explaining their inputs, outputs, and purpose.\n\n5. **Readability:**  \n   - Use intuitive naming conventions and maintain a logical, organized structure throughout your code.\n\n**Note:** When using SCSS, you should be as specific with your nesting as possible. Always nest any selector within all of its parents, even if we do not need to apply styles to the parents.",
            "id": 1740758536309,
            "name": "Coding Standards and Modular Design",
            "type": "component"
        }
      ],
      "id": 1,
      "name": "Components",
      "type": "folder"
    }
]